<Weapon xmlns:xsi="http://www.w3.org/2001/XMLSchema-instance" xmlns:xsd="http://www.w3.org/2001/XMLSchema">

  <Tag_Kinetic>true</Tag_Kinetic>
  <Tag_Energy>false</Tag_Energy>
  <Tag_Guided>false</Tag_Guided>
  <Tag_Missile>false</Tag_Missile>
  <Tag_Plasma>false</Tag_Plasma>
  <Tag_Beam>false</Tag_Beam>
  <Tag_Intercept>false</Tag_Intercept>
  
  <Tag_Bomb>false</Tag_Bomb>
  <Tag_BioWeapon>false</Tag_BioWeapon>
  
  
  <Tag_Drone>false</Tag_Drone>
  <Tag_Torpedo>false</Tag_Torpedo>
  <Tag_Cannon>true</Tag_Cannon>
   
  
  <ExcludesFighters>true</ExcludesFighters>  
  <ExcludesCorvettes>true</ExcludesCorvettes>    
  
  <UID>Assault Cannon Type74</UID>
  <FireDelay>7.5</FireDelay>
  <Range>8700</Range>
  <OrdinanceRequiredToFire>40</OrdinanceRequiredToFire>


  <!-- name of XACT audio cue to play on firing this weapon -->
  <FireCueName>sd_weapon_railgun_massive_01</FireCueName>
  <DieCue>explosionMedium</DieCue>
  <!-- Projectile Information -->
  <DamageAmount>5000</DamageAmount>
  <MuzzleFlash>Yes</MuzzleFlash>
  <ProjectileSpeed>1900</ProjectileSpeed>
  <ExplosionRadius>60</ExplosionRadius> <!-- This projectile explodes -->
  <EffectVsArmor>1.6</EffectVsArmor>
  <EffectVsShields>0.7</EffectVsShields>

  <!-- Animation Information -->
  <Animated>1</Animated>
  <Scale>0.3</Scale>
  <Frames>18</Frames>
  <AnimationPath>Kinetic_Blue_Green_Blue/Kinetic_Blue_Green_Blue_cc</AnimationPath>  
  <LoopAnimation>1</LoopAnimation>       

  <ModelPath>projBall</ModelPath>
  <ProjectileCount>1</ProjectileCount>
  <ProjectileRadius>25</ProjectileRadius>
  <WeaponType>Ballistic Cannon</WeaponType>

<WeaponEffectType>SmokeTrail</WeaponEffectType>
</Weapon>