<Weapon xmlns:xsi="http://www.w3.org/2001/XMLSchema-instance" xmlns:xsd="http://www.w3.org/2001/XMLSchema">
  <UID>SniperHEAP</UID>
  <Tag_Cannon>true</Tag_Cannon>
  <Tag_Kinetic>true</Tag_Kinetic>
    

  <FireDelay>6</FireDelay>
  <Range>8000</Range>
  <PowerRequiredToFire>160</PowerRequiredToFire>
  <OrdinanceRequiredToFire>2</OrdinanceRequiredToFire>

  
  <ExcludesFighters>true</ExcludesFighters>    
  <!-- name of XACT audio cue to play on firing this weapon -->
  <FireCueName>sd_ground_cordrazine_01</FireCueName>
 
  <!-- Projectile Information -->
  <DamageAmount>600</DamageAmount>
  <ArmorPen>1</ArmorPen>
  <ExplosionRadius>33</ExplosionRadius> <!-- This projectile explodes -->
  
  <MuzzleFlash>Yes</MuzzleFlash>
  <ProjectileSpeed>5000</ProjectileSpeed>
  <ProjectileRadius>4</ProjectileRadius>
  <Scale>1.1</Scale>
  <ProjectileTexturePath>projLong_02_orange</ProjectileTexturePath>
  <ModelPath>projLong</ModelPath>
  <WeaponType>Gauss Cannon</WeaponType>
</Weapon>