<?xml version="1.0" encoding="utf-8"?>
<Technology xmlns:xsi="http://www.w3.org/2001/XMLSchema-instance" xmlns:xsd="http://www.w3.org/2001/XMLSchema">
  <UID>OrbitalMissile1</UID>
  <TechnologyType>ShipWeapons</TechnologyType>
  <Cost>400</Cost>
  <RootNode>0</RootNode>
  <Name>OrbitalMissile1</Name>
  <NameIndex>18066</NameIndex>
  <DescriptionIndex>18067</DescriptionIndex>
  <LeadsTo>
    <LeadsToTech>
      <UID>OrbitalMissile2</UID>
    </LeadsToTech>  
  </LeadsTo>
  <ModulesUnlocked>
    <UnlockedMod>
	  <ModuleUID>BroadSide_SRM_2x3</ModuleUID>
	</UnlockedMod>
  </ModulesUnlocked>
</Technology>