<?xml version="1.0"?>
<Weapon xmlns:xsi="http://www.w3.org/2001/XMLSchema-instance" xmlns:xsd="http://www.w3.org/2001/XMLSchema">

  <Tag_Beam>true</Tag_Beam>

  <UID>DualPhasors_3x3</UID>
  <isBeam>true</isBeam>
  <fireDelay>7</fireDelay>
  <Range>3800</Range>
  <PowerRequiredToFire>0</PowerRequiredToFire>
  <OrdinanceRequiredToFire>0</OrdinanceRequiredToFire>
  
  <!-- name of XACT audio cue to play on firing this weapon -->

  <fireCueName>sd_weapon_flame_start_01</fireCueName>
  <ToggleSoundName>sd_weapon_phasor_01</ToggleSoundName>
  <BeamTexture>dualbeam_red</BeamTexture>
  
  <!-- Projectile Information -->
  <DamageAmount>13</DamageAmount>
  <BeamThickness>75</BeamThickness>
  <BeamPowerCostPerSecond>320</BeamPowerCostPerSecond>
  <BeamDuration>1</BeamDuration>
  <WeaponType>Energy Beam</WeaponType>
</Weapon>