<?xml version="1.0" encoding="utf-8"?>
<Technology xmlns:xsi="http://www.w3.org/2001/XMLSchema-instance" xmlns:xsd="http://www.w3.org/2001/XMLSchema">
  <UID>Defence</UID>
  <TechnologyType>General</TechnologyType>
  <Cost>50</Cost>
  <RootNode>1</RootNode>
  <Name>Defence</Name>
  <NameIndex>6507</NameIndex>
  <IconPath>icons_techroot_physics</IconPath>
  <DescriptionIndex>6508</DescriptionIndex>
  <LongDescription>Defence </LongDescription>
  <LeadsTo>
    <LeadsToTech>
      <UID>ArmorTheory</UID>
    </LeadsToTech>
    <LeadsToTech>
      <UID>Plasteel</UID>
    </LeadsToTech>
    <LeadsToTech>
      <UID>ElectronicArmors</UID>
    </LeadsToTech> 
    <LeadsToTech>
      <UID>EnergyShielding</UID>
    </LeadsToTech>
  </LeadsTo>
  <ModulesUnlocked />
  <BuildingsUnlocked />
  <BonusUnlocked />
  <TroopsUnlocked />
  <HullsUnlocked />
</Technology>